Metadata-Version: 2.4
Name: aisuite
Version: 0.1.13
Summary: Uniform access layer for LLMs
License-File: LICENSE
Author: Andrew Ng, Rohit P
Requires-Python: >=3.10,<4.0
Classifier: Programming Language :: Python :: 3
Classifier: Programming Language :: Python :: 3.10
Classifier: Programming Language :: Python :: 3.11
Classifier: Programming Language :: Python :: 3.12
Classifier: Programming Language :: Python :: 3.13
Classifier: Programming Language :: Python :: 3.14
Provides-Extra: all
Provides-Extra: anthropic
Provides-Extra: aws
Provides-Extra: azure
Provides-Extra: cerebras
Provides-Extra: cohere
Provides-Extra: deepgram
Provides-Extra: deepseek
Provides-Extra: google
Provides-Extra: groq
Provides-Extra: huggingface
Provides-Extra: mcp
Provides-Extra: mistral
Provides-Extra: ollama
Provides-Extra: openai
Provides-Extra: watsonx
Requires-Dist: anthropic (>=0.30.1,<0.31.0) ; extra == "anthropic" or extra == "all"
Requires-Dist: boto3 (>=1.34.144,<2.0.0) ; extra == "aws" or extra == "all"
Requires-Dist: cerebras_cloud_sdk (>=1.19.0,<2.0.0) ; extra == "cerebras" or extra == "all"
Requires-Dist: cohere (>=5.12.0,<6.0.0) ; extra == "cohere" or extra == "all"
Requires-Dist: deepgram-sdk (>=5.0.0,<6.0.0) ; extra == "deepgram" or extra == "all"
Requires-Dist: docstring-parser (>=0.14.0,<0.15.0)
Requires-Dist: google-cloud-speech (>=2.33.0,<3.0.0) ; extra == "google" or extra == "all"
Requires-Dist: groq (>=0.9.0,<0.10.0) ; extra == "groq" or extra == "all"
Requires-Dist: httpx (>=0.27.0,<0.28.0)
Requires-Dist: ibm-watsonx-ai (>=1.1.16,<2.0.0) ; extra == "watsonx" or extra == "all"
Requires-Dist: mcp (>=1.1.2,<2.0.0) ; extra == "mcp" or extra == "all"
Requires-Dist: mistralai (>=1.0.3,<2.0.0) ; extra == "mistral" or extra == "all"
Requires-Dist: nest-asyncio (>=1.6.0,<2.0.0) ; extra == "mcp" or extra == "all"
Requires-Dist: numpy (>=1.24.0,<2.0.0) ; extra == "deepgram" or extra == "all"
Requires-Dist: openai (>=1.107.0,<2.0.0) ; extra == "deepseek" or extra == "openai" or extra == "all"
Requires-Dist: scipy (>=1.11.0,<2.0.0) ; extra == "deepgram" or extra == "all"
Requires-Dist: soundfile (>=0.12.1,<0.13.0) ; extra == "deepgram" or extra == "all"
Requires-Dist: vertexai (>=1.63.0,<2.0.0) ; extra == "google" or extra == "all"
